{
	"cmake" : 
	{
		"generator" : 
		{
			"multiConfig" : false,
			"name" : "Ninja"
		},
		"paths" : 
		{
			"cmake" : "C:/Users/F-Gro/AppData/Local/Programs/CLion/bin/cmake/win/x64/bin/cmake.exe",
			"cpack" : "C:/Users/F-Gro/AppData/Local/Programs/CLion/bin/cmake/win/x64/bin/cpack.exe",
			"ctest" : "C:/Users/F-Gro/AppData/Local/Programs/CLion/bin/cmake/win/x64/bin/ctest.exe",
			"root" : "C:/Users/F-Gro/AppData/Local/Programs/CLion/bin/cmake/win/x64/share/cmake-3.26"
		},
		"version" : 
		{
			"isDirty" : false,
			"major" : 3,
			"minor" : 26,
			"patch" : 4,
			"string" : "3.26.4",
			"suffix" : ""
		}
	},
	"objects" : 
	[
		{
			"jsonFile" : "codemodel-v2-df4a2169110aba63743b.json",
			"kind" : "codemodel",
			"version" : 
			{
				"major" : 2,
				"minor" : 5
			}
		},
		{
			"jsonFile" : "cache-v2-53e0c4807dac2e2b0505.json",
			"kind" : "cache",
			"version" : 
			{
				"major" : 2,
				"minor" : 0
			}
		},
		{
			"jsonFile" : "cmakeFiles-v1-89f6528532655ee7ee48.json",
			"kind" : "cmakeFiles",
			"version" : 
			{
				"major" : 1,
				"minor" : 0
			}
		},
		{
			"jsonFile" : "toolchains-v1-c33b70222ee45a6c07ba.json",
			"kind" : "toolchains",
			"version" : 
			{
				"major" : 1,
				"minor" : 0
			}
		}
	],
	"reply" : 
	{
		"cache-v2" : 
		{
			"jsonFile" : "cache-v2-53e0c4807dac2e2b0505.json",
			"kind" : "cache",
			"version" : 
			{
				"major" : 2,
				"minor" : 0
			}
		},
		"cmakeFiles-v1" : 
		{
			"jsonFile" : "cmakeFiles-v1-89f6528532655ee7ee48.json",
			"kind" : "cmakeFiles",
			"version" : 
			{
				"major" : 1,
				"minor" : 0
			}
		},
		"codemodel-v2" : 
		{
			"jsonFile" : "codemodel-v2-df4a2169110aba63743b.json",
			"kind" : "codemodel",
			"version" : 
			{
				"major" : 2,
				"minor" : 5
			}
		},
		"toolchains-v1" : 
		{
			"jsonFile" : "toolchains-v1-c33b70222ee45a6c07ba.json",
			"kind" : "toolchains",
			"version" : 
			{
				"major" : 1,
				"minor" : 0
			}
		}
	}
}
